tw_calculator/__init__.py
tw_calculator/logic.py
tw_calculator-0.0.1.dist-info/LICENSE.txt
tw_calculator-0.0.1.dist-info/METADATA
tw_calculator-0.0.1.dist-info/WHEEL
tw_calculator-0.0.1.dist-info/top_level.txt
tw_calculator-0.0.1.dist-info/RECORD
