Metadata-Version: 2.1
Name: tw-calculator
Version: 0.0.1
Summary: this is test tw_basic_calculator
Home-page: https://github.com/thxawa/py_calculator_module
Author: thxawa
Author-email: thxawa07@gmail.com
Classifier: Programming Language :: Python :: 3
Classifier: License :: OSI Approved :: MIT License
Classifier: Operating System :: OS Independent
Requires-Python: >=3.7
License-File: LICENSE.txt
